bq_test_kit/__init__.py
bq_test_kit/bq_test_kit.py
bq_test_kit/bq_test_kit_config.py
bq_test_kit/constants.py
bq_test_kit/exceptions.py
bq_test_kit/typing.py
bq_test_kit/bq_dsl/__init__.py
bq_test_kit/bq_dsl/bq_query_datum.py
bq_test_kit/bq_dsl/bq_query_results.py
bq_test_kit/bq_dsl/bq_query_template.py
bq_test_kit/bq_dsl/schema_mixin.py
bq_test_kit/bq_dsl/bq_resources/__init__.py
bq_test_kit/bq_dsl/bq_resources/base_bq_resource.py
bq_test_kit/bq_dsl/bq_resources/dataset.py
bq_test_kit/bq_dsl/bq_resources/project.py
bq_test_kit/bq_dsl/bq_resources/resource_strategy.py
bq_test_kit/bq_dsl/bq_resources/table.py
bq_test_kit/bq_dsl/bq_resources/tables.py
bq_test_kit/bq_dsl/bq_resources/data_loaders/__init__.py
bq_test_kit/bq_dsl/bq_resources/data_loaders/base_data_loader.py
bq_test_kit/bq_dsl/bq_resources/data_loaders/dsv_data_loader.py
bq_test_kit/bq_dsl/bq_resources/data_loaders/json_data_loader.py
bq_test_kit/bq_dsl/bq_resources/data_loaders/mixins/__init__.py
bq_test_kit/bq_dsl/bq_resources/data_loaders/mixins/raw_file_loader_mixin.py
bq_test_kit/bq_dsl/bq_resources/partitions/__init__.py
bq_test_kit/bq_dsl/bq_resources/partitions/base_partition.py
bq_test_kit/bq_dsl/bq_resources/partitions/ingestion_time.py
bq_test_kit/bq_dsl/bq_resources/partitions/no_partition.py
bq_test_kit/bq_dsl/bq_resources/partitions/range.py
bq_test_kit/bq_dsl/bq_resources/partitions/time_field.py
bq_test_kit/bq_dsl/bq_resources/partitions/time_partitionning_type.py
bq_test_kit/data_literal_transformers/__init__.py
bq_test_kit/data_literal_transformers/base_data_literal_transformer.py
bq_test_kit/data_literal_transformers/dsv_data_literal_transformer.py
bq_test_kit/data_literal_transformers/json_data_literal_transformer.py
bq_test_kit/data_literal_transformers/json_format.py
bq_test_kit/interpolators/__init__.py
bq_test_kit/interpolators/base_interpolator.py
bq_test_kit/interpolators/jinja_interpolator.py
bq_test_kit/interpolators/shell_interpolator.py
bq_test_kit-0.4.3.dist-info/LICENSE
bq_test_kit-0.4.3.dist-info/METADATA
bq_test_kit-0.4.3.dist-info/WHEEL
bq_test_kit-0.4.3.dist-info/top_level.txt
bq_test_kit-0.4.3.dist-info/RECORD
